<?xml version="1.0" encoding="UTF-8"?>
  <adresboek>
    <contact>
      <id>
        1
      </id>
      <naam>
        <voornaam>
          Joske
        </voornaam>
        <familienaam>
          Vermeulen
        </familienaam>
        <bijnaam></bijnaam>
      </naam>
      <geboortedatum>
        <dag>
          19
        </dag>
        <maand>
          05
        </maand>
        <jaar>
          1986
        </jaar>
      </geboortedatum>
      <tel>
        016/589652
      </tel>
      <email>
        joske@vermeulen.com
      </email>
    </contact>

    <contact>
      <id>
        2
      </id>
      <naam>
        <voornaam>
          Davy
        </voornaam>
        <familienaam>
          Bosman
        </familienaam>
        <bijnaam>
          den bossie
        </bijnaam>
      </naam>
      <geboortedatum>
        <dag></dag>
        <maand></maand>
        <jaar></jaar>
      </geboortedatum>
      <tel>
        016/321954
      </tel>
      <email></email>
    </contact>

  </adresboek>
